pageai_sdk/__init__.py
pageai_sdk/api_client.py
pageai_sdk/configuration.py
pageai_sdk/exceptions.py
pageai_sdk/rest.py
pageai_sdk/api/__init__.py
pageai_sdk/api/page_ai_api.py
pageai_sdk/models/__init__.py
pageai_sdk/models/upload_response.py
pageai_sdk-0.6.0.210.dist-info/METADATA
pageai_sdk-0.6.0.210.dist-info/WHEEL
pageai_sdk-0.6.0.210.dist-info/top_level.txt
pageai_sdk-0.6.0.210.dist-info/RECORD
